PysisR/__init__.py
PysisR/plugin.py
pysisr-1.1.1.dist-info/METADATA
pysisr-1.1.1.dist-info/WHEEL
pysisr-1.1.1.dist-info/top_level.txt
pysisr-1.1.1.dist-info/RECORD
