Metadata-Version: 2.4
Name: PysisR
Version: 1.1.1
Summary: pip package minimum easy
Requires-Python: >=3.7
Dynamic: description
Dynamic: description-content-type
Dynamic: requires-python
Dynamic: summary
